{
  "CREATE": {
    "/ServiceId": "<FASTLY_SERVICE_ID>",
    "/VersionId": "<FASTLY_VERSION_ID>",
    "/Name": "aws.amazon.com",
    "/Address": "aws.amazon.com",
    "/Comment": "Hello AWS",
    "/Port": 443,
    "/UseSsl": true,
    "/MinTlsVersion": "1.0",
    "/MaxTlsVersion": null,
    "/Weight": 1,
    "/Ipv4": null,
    "/Ipv6": null,
    "/Hostname": null,
    "/OverrideHost": null,
    "/Healthcheck": null,
    "/Shield": null,
    "/RequestCondition": null,
    "/SslCaCert": null,
    "/SslCertHostname": null,
    "/SslCheckCert": null,
    "/SslCiphers": null,
    "/SslClientCert": null,
    "/SslClientKey": null,
    "/BetweenBytesTimeout": 4096,
    "/ConnectTimeout": 500,
    "/FirstByteTimeout": 50,
    "/MaxConn": 10
  },
  "UPDATE": {
    "/Address": "amazon.com",
    "/Comment": "Hello Amazon",
    "/Port": 443,
    "/UseSsl": true,
    "/MinTlsVersion": "1.<FASTLY_VERSION_ID>",
    "/MaxTlsVersion": null,
    "/Weight": <FASTLY_VERSION_ID>,
    "/Ipv4": null,
    "/Ipv6": null,
    "/Hostname": null,
    "/OverrideHost": null,
    "/Healthcheck": null,
    "/Shield": null,
    "/RequestCondition": null,
    "/SslCaCert": null,
    "/SslCertHostname": null,
    "/SslCheckCert": null,
    "/SslCiphers": null,
    "/SslClientCert": null,
    "/SslClientKey": null,
    "/BetweenBytesTimeout": 10,
    "/ConnectTimeout": <FASTLY_VERSION_ID>00,
    "/FirstByteTimeout": 10,
    "/MaxConn": <FASTLY_VERSION_ID>0
  }
}